{"id":0,"name":"ITIL H7","translatedName":"ITIL H7","learning":"1","learningFrom":"1","modes":null,"content":[{"to":"Coordineren processen voor leveren IT-services aan klanten","from":["Doel H7 Serviceproductiefase","",""]},{"to":"IT-services -Servicemanagementprocessen -Hardware -IT’ers en niet IT’ers","from":["Wat is het bereik van H7 Serviceproductiefase","",""]},{"to":"Tevredenheid in stand houden -Service-onderbreking impact minimaliseren -Authoriuzed toegang verlenen","from":["Doelstellingen H7 Serviceproductiefase","",""]},{"to":"1. Eventmanagement 2. Incidentmanagement 3. Request fulfillment 4. Problemmamnagement 5. Accessmanagement","from":["Volgorde hoofdstukken","",""]},{"to":"Beheersing event gedurende levenscylus","from":["Doel Eventmanagement","",""]},{"to":"Eventmanagement","from":["Welk proces zorgt voor vroegtijdige incidentendetectie","",""]},{"to":"Ja","from":["Automatiseerd Eventmanagement activiteiten","",""]},{"to":"Nee","from":["Automatiseerd Eventmanagement events","",""]},{"to":"Incidenten herstellen om negatieve gevolgen te beperken","from":["Doel Incidentmanagement","",""]},{"to":"Incidenten volgen en oplossen en Incidenten prioritiseren","from":["Wat is de waarde van Incidentmanagement","",""]},{"to":"Managen requests","from":["Doel Request fulfillment","",""]},{"to":"Snel en effectief verbeteren","from":["Waarom Request fulfillment","",""]},{"to":"Hulpkanaal -Informatie beschikbaar -Assisteren klachten","from":["Doelstellingen van Request fulfillment","",""]},{"to":"Managen problemen","from":["Doel Problemmamnagement","",""]},{"to":"Incident activiteiten","from":["Bereik Problemmamnagement","",""]},{"to":"Problemmamnagement","from":["Welk proces versnelt MTRS","",""]},{"to":"Problemmamnagement","from":["Welk proces creeert workarounds","",""]},{"to":"Problemen elimineren en voorkome om impact te minimaliseren","from":["Wat is de primaire doelstelling van Problemmamnagement","",""]},{"to":"Gemachtigde recht geven","from":["Doel Accessmanagement","",""]},{"to":"Gebruikers met rechten","from":["Breik Accessmanagement","",""]},{"to":"Permissies op orde hebben","from":["Waarom Accessmanagement","",""]},{"to":"Nee","from":["Zorgt Incidentmanagement voor het voorkomen van Incidenten","",""]},{"to":"Beide","from":["Is Request fulfillment voor intern en of extern","",""]}]}